image_processing/__init__.py
image_processing/processing.py
processing_image_alquimista-0.0.1.dist-info/METADATA
processing_image_alquimista-0.0.1.dist-info/WHEEL
processing_image_alquimista-0.0.1.dist-info/top_level.txt
processing_image_alquimista-0.0.1.dist-info/RECORD
